<annotation>
	<folder>images</folder>
	<filename>df0e4163ce81ebfe08e166ab82cafa89.png</filename>
	<path>D:\labelimgdata\images\df0e4163ce81ebfe08e166ab82cafa89.png</path>
	<source>
		<database>Unknown</database>
	</source>
	<size>
		<width>1500</width>
		<height>1126</height>
		<depth>3</depth>
	</size>
	<segmented>0</segmented>
	<object>
		<name>Table</name>
		<pose>Unspecified</pose>
		<truncated>0</truncated>
		<difficult>0</difficult>
		<bndbox>
			<xmin>29</xmin>
			<ymin>445</ymin>
			<xmax>1476</xmax>
			<ymax>628</ymax>
		</bndbox>
	</object>
</annotation>
