<annotation>
	<folder>images4</folder>
	<filename>13.png</filename>
	<path>D:\labelimgdata\images4\13.png</path>
	<source>
		<database>Unknown</database>
	</source>
	<size>
		<width>301</width>
		<height>241</height>
		<depth>3</depth>
	</size>
	<segmented>0</segmented>
	<object>
		<name>Table</name>
		<pose>Unspecified</pose>
		<truncated>0</truncated>
		<difficult>0</difficult>
		<bndbox>
			<xmin>9</xmin>
			<ymin>147</ymin>
			<xmax>288</xmax>
			<ymax>208</ymax>
		</bndbox>
	</object>
</annotation>
