<annotation>
	<folder>images4</folder>
	<filename>49.jpg</filename>
	<path>D:\labelimgdata\images4\49.jpg</path>
	<source>
		<database>Unknown</database>
	</source>
	<size>
		<width>1218</width>
		<height>1042</height>
		<depth>3</depth>
	</size>
	<segmented>0</segmented>
	<object>
		<name>Table</name>
		<pose>Unspecified</pose>
		<truncated>0</truncated>
		<difficult>0</difficult>
		<bndbox>
			<xmin>4</xmin>
			<ymin>278</ymin>
			<xmax>1217</xmax>
			<ymax>885</ymax>
		</bndbox>
	</object>
</annotation>
